{"frames": {

"sterren-01":
{
	"frame": {"x":1,"y":1,"w":50,"h":50},
	"rotated": false,
	"trimmed": false,
	"spriteSourceSize": {"x":0,"y":0,"w":50,"h":50},
	"sourceSize": {"w":50,"h":50}
},
"sterren-02":
{
	"frame": {"x":53,"y":1,"w":50,"h":50},
	"rotated": false,
	"trimmed": false,
	"spriteSourceSize": {"x":0,"y":0,"w":50,"h":50},
	"sourceSize": {"w":50,"h":50}
},
"sterren-03":
{
	"frame": {"x":105,"y":1,"w":50,"h":50},
	"rotated": false,
	"trimmed": false,
	"spriteSourceSize": {"x":0,"y":0,"w":50,"h":50},
	"sourceSize": {"w":50,"h":50}
},
"sterren-04":
{
	"frame": {"x":157,"y":1,"w":50,"h":50},
	"rotated": false,
	"trimmed": false,
	"spriteSourceSize": {"x":0,"y":0,"w":50,"h":50},
	"sourceSize": {"w":50,"h":50}
},
"sterren-05":
{
	"frame": {"x":209,"y":1,"w":50,"h":50},
	"rotated": false,
	"trimmed": false,
	"spriteSourceSize": {"x":0,"y":0,"w":50,"h":50},
	"sourceSize": {"w":50,"h":50}
},
"sterren-06":
{
	"frame": {"x":261,"y":1,"w":50,"h":50},
	"rotated": false,
	"trimmed": false,
	"spriteSourceSize": {"x":0,"y":0,"w":50,"h":50},
	"sourceSize": {"w":50,"h":50}
},
"sterren-07":
{
	"frame": {"x":313,"y":1,"w":50,"h":50},
	"rotated": false,
	"trimmed": false,
	"spriteSourceSize": {"x":0,"y":0,"w":50,"h":50},
	"sourceSize": {"w":50,"h":50}
},
"sterren-08":
{
	"frame": {"x":365,"y":1,"w":50,"h":50},
	"rotated": false,
	"trimmed": false,
	"spriteSourceSize": {"x":0,"y":0,"w":50,"h":50},
	"sourceSize": {"w":50,"h":50}
}},
"meta": {
	"app": "http://www.codeandweb.com/texturepacker",
	"version": "1.0",
	"image": "windroos.png",
	"format": "RGBA8888",
	"size": {"w":416,"h":52},
	"scale": "1",
	"smartupdate": "$TexturePacker:SmartUpdate:23d510e93614a7656d17d637f9475191:57095fd2f7abcd3b6a3ae36d6822482d:c5a23551fe81a88434fb34bedf8e27eb$"
}
}
